{
  "posts": [
    {
      "id": 1,
      "title": "json-server",
      "author": "typicode"
    }
  ],
  "comments": [
    {
      "id": 1,
      "body": "some comment",
      "postId": 1
    },
    {
      "headers": {
        "Accept": "application/json",
        "data": {
          "content": "fafaf"
        }
      },
      "id": 2
    },
    {
      "headers": {
        "Accept": "application/json",
        "data": {
          "content": "fafaf"
        }
      },
      "id": 3
    },
    {
      "headers": {
        "Accept": "application/json",
        "data": {
          "content": "fafafええええ\n",
          "tel": "0302024920",
          "mailAddress": "aba@cc.jp",
          "userNameKana": "fafa",
          "userName": "森田",
          "corporateName": "えええ"
        }
      },
      "id": 4
    },
    {
      "headers": {
        "Accept": "application/json",
        "data": {
          "tel": "0000000000"
        }
      },
      "id": 5
    },
    {
      "headers": {
        "Accept": "application/json",
        "data": {
          "tel": "000000000"
        }
      },
      "id": 6
    },
    {
      "headers": {
        "Accept": "application/json",
        "data": {
          "tel": "000000000"
        }
      },
      "id": 7
    },
    {
      "headers": {
        "Accept": "application/json",
        "data": {
          "tel": "000000000"
        }
      },
      "id": 8
    },
    {
      "headers": {
        "Accept": "application/json",
        "data": {
          "tel": "000000000"
        }
      },
      "id": 9
    }
  ],
  "profile": {
    "name": "typicode"
  }
}